LICENSE.txt
README.rst
setup.py
pyverilator/__init__.py
pyverilator/__main__.py
pyverilator/pyverilator.py
pyverilator/verilator_tools.py
pyverilator/verilatorcpp.py
pyverilator_mm.egg-info/PKG-INFO
pyverilator_mm.egg-info/SOURCES.txt
pyverilator_mm.egg-info/dependency_links.txt
pyverilator_mm.egg-info/requires.txt
pyverilator_mm.egg-info/top_level.txt