Metadata-Version: 2.1
Name: pyverilator-mm
Version: 0.7.6
Summary: Python interface to Verilator models
Home-page: https://github.com/bat52/pyverilator
Author: CSAIL CSG, Marco Merlin
Author-email: acwright@mit.edu, bthom@mit.edu
License: UNKNOWN
Project-URL: Bug Reports, https://github.com/bat52/pyverilator/issues
Project-URL: Source, https://github.com/bat52/pyverilator
Keywords: Verilator Wrapper Verilog
Platform: UNKNOWN
Classifier: Development Status :: 3 - Alpha
Classifier: Intended Audience :: Developers
Classifier: Topic :: Software Development :: Build Tools
Classifier: Topic :: System :: Hardware
Classifier: License :: OSI Approved :: MIT License
Classifier: Programming Language :: Python :: 3.5
Classifier: Programming Language :: Python :: 3.6
License-File: LICENSE.txt
